{
  "type": "FeatureCollection",
  "crs": {
    "type": "name",
    "properties": {
      "name": "EPSG:4326"
    }
  },
  "features": [
    {
      "type": "Feature",
      "id": 20591,
      "geometry": {
        "type": "Polygon",
        "coordinates": [
          [
            [
              -114.47993169198,
              32.873338199081
            ],
            [
              -114.480307955829,
              32.8737363751861
            ],
            [
              -114.48112821021,
              32.8741408696439
            ],
            [
              -114.48197104105,
              32.8750320148192
            ],
            [
              -114.482753668597,
              32.8758978702237
            ],
            [
              -114.483671751309,
              32.8771492387934
            ],
            [
              -114.484574783647,
              32.8787797821281
            ],
            [
              -114.484898370287,
              32.8803913371396
            ],
            [
              -114.483528770957,
              32.8812318616577
            ],
            [
              -114.482166697712,
              32.8810549094326
            ],
            [
              -114.4807293708,
              32.8807073243499
            ],
            [
              -114.4792845187,
              32.880922195975
            ],
            [
              -114.477335474571,
              32.8814214527737
            ],
            [
              -114.475740116932,
              32.8813203380149
            ],
            [
              -114.474235063335,
              32.8814024939067
            ],
            [
              -114.472963292337,
              32.8810928280657
            ],
            [
              -114.473384707308,
              32.879215853228
            ],
            [
              -114.474009305026,
              32.8775347572301
            ],
            [
              -114.474310316105,
              32.8761253935073
            ],
            [
              -114.474919862551,
              32.876251794157
            ],
            [
              -114.474648953119,
              32.8771618778906
            ],
            [
              -114.474551124788,
              32.8778697150054
            ],
            [
              -114.475002640508,
              32.8787861019379
            ],
            [
              -114.475619712141,
              32.8793296091757
            ],
            [
              -114.477418252528,
              32.8792095326944
            ],
            [
              -114.478900729665,
              32.8789377787467
            ],
            [
              -114.480247753433,
              32.8782109913657
            ],
            [
              -114.480089722707,
              32.8767763578321
            ],
            [
              -114.479961792729,
              32.8749814534326
            ],
            [
              -114.479961792729,
              32.8738880613899
            ],
            [
              -114.47993169198,
              32.873338199081
            ]
          ]
        ]
      },
      "properties": {
        "OBJECTID": 20591,
        "poly_IncidentName": "McKinley",
        "poly_FeatureCategory": "Wildfire Daily Fire Perimeter",
        "poly_MapMethod": "Mixed Methods",
        "poly_GISAcres": null,
        "poly_CreateDate": 1668852324835,
        "poly_DateCurrent": 1668852324835,
        "poly_PolygonDateTime": null,
        "poly_Acres_AutoCalc": 107.245714035641,
        "poly_GlobalID": "{C34412E0-14D6-4616-A574-1A58B29AD613}",
        "poly_Source": "2022 NIFS",
        "irwin_ABCDMisc": null,
        "irwin_ADSPermissionState": "DEFAULT",
        "irwin_CalculatedAcres": null,
        "irwin_ContainmentDateTime": null,
        "irwin_ControlDateTime": null,
        "irwin_DailyAcres": 107,
        "irwin_DiscoveryAcres": 0.1,
        "irwin_DispatchCenterID": "AZPDC",
        "irwin_EstimatedCostToDate": null,
        "irwin_FFReportApprovedByTitle": null,
        "irwin_FFReportApprovedByUnit": null,
        "irwin_FFReportApprovedDate": null,
        "irwin_FireBehaviorGeneral": null,
        "irwin_FireBehaviorGeneral1": null,
        "irwin_FireBehaviorGeneral2": null,
        "irwin_FireBehaviorGeneral3": null,
        "irwin_FireCause": "Undetermined",
        "irwin_FireCauseGeneral": null,
        "irwin_FireCauseSpecific": null,
        "irwin_FireCode": "P4M1",
        "irwin_FireDepartmentID": null,
        "irwin_FireDiscoveryDateTime": 1668832200000,
        "irwin_FireMgmtComplexity": null,
        "irwin_FireOutDateTime": null,
        "irwin_FSConfinePercent": null,
        "irwin_FSFullSuppPercent": null,
        "irwin_FSMonitorPercent": null,
        "irwin_FSPointZonePercent": null,
        "irwin_FSJobCode": "PD",
        "irwin_FSOverrideCode": "1522",
        "irwin_GACC": "SWCC",
        "irwin_ICS209ReportDateTime": null,
        "irwin_ICS209RForTimePeriodFrom": null,
        "irwin_ICS209RForTimePeriodTo": null,
        "irwin_ICS209ReportStatus": null,
        "irwin_IncidentManagementOrg": null,
        "irwin_IncidentName": "McKinley  ",
        "irwin_IncidentShortDescription": null,
        "irwin_IncidentTypeCategory": "WF",
        "irwin_IncidentTypeKind": "FI",
        "irwin_InitialLatitude": 32.88474,
        "irwin_InitialLongitude": -114.486,
        "irwin_InitialResponseAcres": null,
        "irwin_InitialResponseDateTime": null,
        "irwin_IrwinID": "{4580BDCB-9C44-4986-9BB8-ECF390E23A80}",
        "irwin_IsFireCauseInvestigated": null,
        "irwin_IsFireCodeRequested": 0,
        "irwin_IsFSAssisted": 1,
        "irwin_IsMultiJurisdictional": 0,
        "irwin_IsReimbursable": 0,
        "irwin_IsTrespass": 1,
        "irwin_IsUnifiedCommand": null,
        "irwin_LocalIncidentIdentifier": "001419",
        "irwin_PercentContained": null,
        "irwin_PercentPerToBeContained": null,
        "irwin_POOCity": null,
        "irwin_POOCounty": "Imperial",
        "irwin_POODispatchCenterID": "AZPDC",
        "irwin_POOFips": "06025",
        "irwin_POOJurisdictionalAgency": "BLM",
        "irwin_POOJurisdictionalUnit": "AZCRD",
        "irwin_POOJurisdUnitParentUnit": null,
        "irwin_POOLandownerCategory": "BLM",
        "irwin_POOLandownerKind": "Federal",
        "irwin_POOLegalDescPrinMeridian": null,
        "irwin_POOLegalDescQtr": null,
        "irwin_POOLegalDescQtrQtr": null,
        "irwin_POOLegalDescRange": null,
        "irwin_POOLegalDescSection": null,
        "irwin_POOLegalDescTownship": null,
        "irwin_POOPredServiceAreaID": "SW03",
        "irwin_POOProtectingAgency": "BLM",
        "irwin_POOProtectingUnit": "AZCRD",
        "irwin_POOState": "US-CA",
        "irwin_PredominantFuelGroup": null,
        "irwin_PredominantFuelModel": null,
        "irwin_PrimaryFuelModel": null,
        "irwin_SecondaryFuelModel": null,
        "irwin_TotalIncidentPersonnel": null,
        "irwin_UniqueFireIdentifier": "2022-AZCRD-001419",
        "irwin_WFDSSDecisionStatus": "No Decision",
        "irwin_CreatedBySystem": "wildcad",
        "irwin_ModifiedBySystem": "wildcad",
        "irwin_IsDispatchComplete": 0,
        "irwin_OrganizationalAssessment": null,
        "irwin_StratDecisionPublishDate": null,
        "irwin_GlobalID": null,
        "irwin_Source": "IRWIN",
        "irwin_ArchivedOn": null,
        "irwin_ModifiedOnDateTime_dt": 1669047904137,
        "irwin_CreatedOnDateTime_dt": 1668837918033,
        "Shape__Area": 4.18188792536967e-05,
        "Shape__Length": 0.0402783922643493,
        "GlobalID": "253db7e9-abea-4e15-b3db-bbe33e980a12",
        "irwin_IsCpxChild": 0,
        "irwin_CpxName": null,
        "irwin_CpxID": null
      }
    }
  ]
}
