{
  "type": "FeatureCollection",
  "crs": {
    "type": "name",
    "properties": {
      "name": "EPSG:4326"
    }
  },
  "features": [
    {
      "type": "Feature",
      "id": 14913,
      "geometry": {
        "type": "Polygon",
        "coordinates": [
          [
            [
              -117.272319362194,
              34.1766761716351
            ],
            [
              -117.272309303911,
              34.176681857869
            ],
            [
              -117.272308800996,
              34.1766689598354
            ],
            [
              -117.272319362194,
              34.1766761716351
            ]
          ]
        ]
      },
      "properties": {
        "OBJECTID": 14913,
        "poly_IncidentName": "WILDWOOD",
        "poly_FeatureCategory": "Wildfire Daily Fire Perimeter",
        "poly_MapMethod": "Hand Sketch",
        "poly_GISAcres": null,
        "poly_CreateDate": 1642453058796,
        "poly_DateCurrent": null,
        "poly_PolygonDateTime": null,
        "poly_Acres_AutoCalc": null,
        "poly_GlobalID": null,
        "poly_Source": "Inspector",
        "irwin_ABCDMisc": null,
        "irwin_ADSPermissionState": "DEFAULT",
        "irwin_CalculatedAcres": null,
        "irwin_ContainmentDateTime": null,
        "irwin_ControlDateTime": null,
        "irwin_DailyAcres": 0.1,
        "irwin_DiscoveryAcres": 1,
        "irwin_DispatchCenterID": "CASBCC",
        "irwin_EstimatedCostToDate": null,
        "irwin_FFReportApprovedByTitle": null,
        "irwin_FFReportApprovedByUnit": null,
        "irwin_FFReportApprovedDate": null,
        "irwin_FireBehaviorGeneral": null,
        "irwin_FireBehaviorGeneral1": null,
        "irwin_FireBehaviorGeneral2": null,
        "irwin_FireBehaviorGeneral3": null,
        "irwin_FireCause": "Undetermined",
        "irwin_FireCauseGeneral": "Undetermined",
        "irwin_FireCauseSpecific": null,
        "irwin_FireCode": null,
        "irwin_FireDepartmentID": null,
        "irwin_FireDiscoveryDateTime": 1627905557000,
        "irwin_FireMgmtComplexity": null,
        "irwin_FireOutDateTime": null,
        "irwin_FSConfinePercent": null,
        "irwin_FSFullSuppPercent": null,
        "irwin_FSMonitorPercent": null,
        "irwin_FSPointZonePercent": null,
        "irwin_FSJobCode": null,
        "irwin_FSOverrideCode": null,
        "irwin_GACC": "OSCC",
        "irwin_ICS209ReportDateTime": null,
        "irwin_ICS209RForTimePeriodFrom": null,
        "irwin_ICS209RForTimePeriodTo": null,
        "irwin_ICS209ReportStatus": null,
        "irwin_IncidentManagementOrg": null,
        "irwin_IncidentName": "WILDWOOD",
        "irwin_IncidentShortDescription": null,
        "irwin_IncidentTypeCategory": "WF",
        "irwin_IncidentTypeKind": "FI",
        "irwin_InitialLatitude": 34.17598,
        "irwin_InitialLongitude": -117.2779,
        "irwin_InitialResponseAcres": null,
        "irwin_InitialResponseDateTime": null,
        "irwin_IrwinID": "{86033CF1-DC70-47E2-BF71-55DDE3046202}",
        "irwin_IsFireCauseInvestigated": null,
        "irwin_IsFireCodeRequested": 0,
        "irwin_IsFSAssisted": 0,
        "irwin_IsMultiJurisdictional": 0,
        "irwin_IsReimbursable": 0,
        "irwin_IsTrespass": 0,
        "irwin_IsUnifiedCommand": null,
        "irwin_LocalIncidentIdentifier": "011813",
        "irwin_PercentContained": null,
        "irwin_PercentPerToBeContained": null,
        "irwin_POOCity": null,
        "irwin_POOCounty": "San Bernardino",
        "irwin_POODispatchCenterID": "CASBCC",
        "irwin_POOFips": "06071",
        "irwin_POOJurisdictionalAgency": null,
        "irwin_POOJurisdictionalUnit": null,
        "irwin_POOJurisdUnitParentUnit": null,
        "irwin_POOLandownerCategory": "Private",
        "irwin_POOLandownerKind": "Private",
        "irwin_POOLegalDescPrinMeridian": null,
        "irwin_POOLegalDescQtr": null,
        "irwin_POOLegalDescQtrQtr": null,
        "irwin_POOLegalDescRange": null,
        "irwin_POOLegalDescSection": null,
        "irwin_POOLegalDescTownship": null,
        "irwin_POOPredServiceAreaID": "SC10",
        "irwin_POOProtectingAgency": "FS",
        "irwin_POOProtectingUnit": "CABDF",
        "irwin_POOState": "US-CA",
        "irwin_PredominantFuelGroup": null,
        "irwin_PredominantFuelModel": null,
        "irwin_PrimaryFuelModel": null,
        "irwin_SecondaryFuelModel": null,
        "irwin_TotalIncidentPersonnel": null,
        "irwin_UniqueFireIdentifier": "2021-CABDF-011813",
        "irwin_WFDSSDecisionStatus": "No Decision",
        "irwin_CreatedBySystem": "wildcad",
        "irwin_ModifiedBySystem": "INFORM_Inspector",
        "irwin_IsDispatchComplete": 0,
        "irwin_OrganizationalAssessment": null,
        "irwin_StratDecisionPublishDate": null,
        "irwin_GlobalID": null,
        "irwin_Source": "IRWIN",
        "irwin_ArchivedOn": null,
        "irwin_ModifiedOnDateTime_dt": 1642453081663,
        "irwin_CreatedOnDateTime_dt": 1627912150493,
        "Shape__Area": 6.63931132294238e-11,
        "Shape__Length": 3.7250780812374e-05,
        "GlobalID": "433f4b70-3204-4ac1-9890-eaea44579ac4",
        "irwin_IsCpxChild": 0,
        "irwin_CpxName": null,
        "irwin_CpxID": null
      }
    },
    {
      "type": "Feature",
      "id": 14902,
      "geometry": {
        "type": "Polygon",
        "coordinates": [
          [
            [
              -117.436130845383,
              34.2459549605703
            ],
            [
              -117.43611810489,
              34.2459627207541
            ],
            [
              -117.436117434338,
              34.2459455375078
            ],
            [
              -117.436129169003,
              34.2459535748331
            ],
            [
              -117.436130845383,
              34.2459549605703
            ]
          ]
        ]
      },
      "properties": {
        "OBJECTID": 14902,
        "poly_IncidentName": "MATHEWS",
        "poly_FeatureCategory": "Wildfire Daily Fire Perimeter",
        "poly_MapMethod": "Hand Sketch",
        "poly_GISAcres": null,
        "poly_CreateDate": 1642452686732,
        "poly_DateCurrent": null,
        "poly_PolygonDateTime": null,
        "poly_Acres_AutoCalc": null,
        "poly_GlobalID": null,
        "poly_Source": "Inspector",
        "irwin_ABCDMisc": null,
        "irwin_ADSPermissionState": "DEFAULT",
        "irwin_CalculatedAcres": 0.1,
        "irwin_ContainmentDateTime": null,
        "irwin_ControlDateTime": null,
        "irwin_DailyAcres": 0.1,
        "irwin_DiscoveryAcres": 0.1,
        "irwin_DispatchCenterID": "CABDCC",
        "irwin_EstimatedCostToDate": null,
        "irwin_FFReportApprovedByTitle": null,
        "irwin_FFReportApprovedByUnit": null,
        "irwin_FFReportApprovedDate": null,
        "irwin_FireBehaviorGeneral": null,
        "irwin_FireBehaviorGeneral1": null,
        "irwin_FireBehaviorGeneral2": null,
        "irwin_FireBehaviorGeneral3": null,
        "irwin_FireCause": "Undetermined",
        "irwin_FireCauseGeneral": "Undetermined",
        "irwin_FireCauseSpecific": null,
        "irwin_FireCode": null,
        "irwin_FireDepartmentID": null,
        "irwin_FireDiscoveryDateTime": 1632020419000,
        "irwin_FireMgmtComplexity": null,
        "irwin_FireOutDateTime": null,
        "irwin_FSConfinePercent": null,
        "irwin_FSFullSuppPercent": null,
        "irwin_FSMonitorPercent": null,
        "irwin_FSPointZonePercent": null,
        "irwin_FSJobCode": null,
        "irwin_FSOverrideCode": null,
        "irwin_GACC": "OSCC",
        "irwin_ICS209ReportDateTime": null,
        "irwin_ICS209RForTimePeriodFrom": null,
        "irwin_ICS209RForTimePeriodTo": null,
        "irwin_ICS209ReportStatus": null,
        "irwin_IncidentManagementOrg": null,
        "irwin_IncidentName": "MATHEWS",
        "irwin_IncidentShortDescription": null,
        "irwin_IncidentTypeCategory": "WF",
        "irwin_IncidentTypeKind": "FI",
        "irwin_InitialLatitude": 34.245938,
        "irwin_InitialLongitude": -117.436085,
        "irwin_InitialResponseAcres": null,
        "irwin_InitialResponseDateTime": null,
        "irwin_IrwinID": "{D1A7ECF8-570D-42B2-AD67-A744BBD40AEC}",
        "irwin_IsFireCauseInvestigated": null,
        "irwin_IsFireCodeRequested": 0,
        "irwin_IsFSAssisted": 0,
        "irwin_IsMultiJurisdictional": 0,
        "irwin_IsReimbursable": 0,
        "irwin_IsTrespass": 0,
        "irwin_IsUnifiedCommand": null,
        "irwin_LocalIncidentIdentifier": "013623",
        "irwin_PercentContained": null,
        "irwin_PercentPerToBeContained": null,
        "irwin_POOCity": null,
        "irwin_POOCounty": "San Bernardino",
        "irwin_POODispatchCenterID": "CASBCC",
        "irwin_POOFips": "06071",
        "irwin_POOJurisdictionalAgency": null,
        "irwin_POOJurisdictionalUnit": null,
        "irwin_POOJurisdUnitParentUnit": null,
        "irwin_POOLandownerCategory": "Private",
        "irwin_POOLandownerKind": "Private",
        "irwin_POOLegalDescPrinMeridian": null,
        "irwin_POOLegalDescQtr": null,
        "irwin_POOLegalDescQtrQtr": null,
        "irwin_POOLegalDescRange": null,
        "irwin_POOLegalDescSection": null,
        "irwin_POOLegalDescTownship": null,
        "irwin_POOPredServiceAreaID": "SC09",
        "irwin_POOProtectingAgency": "CDF",
        "irwin_POOProtectingUnit": "CABDU",
        "irwin_POOState": "US-CA",
        "irwin_PredominantFuelGroup": null,
        "irwin_PredominantFuelModel": null,
        "irwin_PrimaryFuelModel": null,
        "irwin_SecondaryFuelModel": null,
        "irwin_TotalIncidentPersonnel": null,
        "irwin_UniqueFireIdentifier": "2021-CABDU-013623",
        "irwin_WFDSSDecisionStatus": "No Decision",
        "irwin_CreatedBySystem": "cfcad",
        "irwin_ModifiedBySystem": "INFORM_Inspector",
        "irwin_IsDispatchComplete": 0,
        "irwin_OrganizationalAssessment": null,
        "irwin_StratDecisionPublishDate": null,
        "irwin_GlobalID": null,
        "irwin_Source": "IRWIN",
        "irwin_ArchivedOn": null,
        "irwin_ModifiedOnDateTime_dt": 1642458508623,
        "irwin_CreatedOnDateTime_dt": 1632021766140,
        "Shape__Area": 1.1323209037073e-10,
        "Shape__Length": 4.85123497385117e-05,
        "GlobalID": "2d51db4f-4582-461c-9f8d-4b3985b30590",
        "irwin_IsCpxChild": 0,
        "irwin_CpxName": null,
        "irwin_CpxID": null
      }
    },
    {
      "type": "Feature",
      "id": 14898,
      "geometry": {
        "type": "Polygon",
        "coordinates": [
          [
            [
              -115.979104430721,
              33.585625641089
            ],
            [
              -115.979088002191,
              33.5856253617839
            ],
            [
              -115.979074591146,
              33.5856222894272
            ],
            [
              -115.979071238384,
              33.5856119551357
            ],
            [
              -115.979072244213,
              33.58560413459
            ],
            [
              -115.979087666915,
              33.5855946382122
            ],
            [
              -115.979106442378,
              33.5856063690317
            ],
            [
              -115.979104430721,
              33.585625641089
            ]
          ]
        ]
      },
      "properties": {
        "OBJECTID": 14898,
        "poly_IncidentName": "BOX",
        "poly_FeatureCategory": "Wildfire Daily Fire Perimeter",
        "poly_MapMethod": "Hand Sketch",
        "poly_GISAcres": null,
        "poly_CreateDate": 1642274957126,
        "poly_DateCurrent": 1642274957126,
        "poly_PolygonDateTime": null,
        "poly_Acres_AutoCalc": 0.00208629412693409,
        "poly_GlobalID": "{A48E6E36-3990-4CBE-BCA0-22722A782A4B}",
        "poly_Source": "2022 NIFS",
        "irwin_ABCDMisc": null,
        "irwin_ADSPermissionState": "DEFAULT",
        "irwin_CalculatedAcres": 0.01,
        "irwin_ContainmentDateTime": null,
        "irwin_ControlDateTime": null,
        "irwin_DailyAcres": 0.1,
        "irwin_DiscoveryAcres": 0.1,
        "irwin_DispatchCenterID": "CASBCC",
        "irwin_EstimatedCostToDate": null,
        "irwin_FFReportApprovedByTitle": null,
        "irwin_FFReportApprovedByUnit": null,
        "irwin_FFReportApprovedDate": null,
        "irwin_FireBehaviorGeneral": null,
        "irwin_FireBehaviorGeneral1": null,
        "irwin_FireBehaviorGeneral2": null,
        "irwin_FireBehaviorGeneral3": null,
        "irwin_FireCause": "Undetermined",
        "irwin_FireCauseGeneral": "Undetermined",
        "irwin_FireCauseSpecific": "Origin and/or cause not identified",
        "irwin_FireCode": "PE27",
        "irwin_FireDepartmentID": null,
        "irwin_FireDiscoveryDateTime": 1641873600000,
        "irwin_FireMgmtComplexity": null,
        "irwin_FireOutDateTime": null,
        "irwin_FSConfinePercent": null,
        "irwin_FSFullSuppPercent": null,
        "irwin_FSMonitorPercent": null,
        "irwin_FSPointZonePercent": null,
        "irwin_FSJobCode": null,
        "irwin_FSOverrideCode": null,
        "irwin_GACC": "OSCC",
        "irwin_ICS209ReportDateTime": null,
        "irwin_ICS209RForTimePeriodFrom": null,
        "irwin_ICS209RForTimePeriodTo": null,
        "irwin_ICS209ReportStatus": null,
        "irwin_IncidentManagementOrg": null,
        "irwin_IncidentName": "BOX",
        "irwin_IncidentShortDescription": null,
        "irwin_IncidentTypeCategory": "WF",
        "irwin_IncidentTypeKind": "FI",
        "irwin_InitialLatitude": 33.58561,
        "irwin_InitialLongitude": -115.9788,
        "irwin_InitialResponseAcres": null,
        "irwin_InitialResponseDateTime": 1641945600000,
        "irwin_IrwinID": "{C9B3A7EB-BD92-499F-98B5-69CDDF0E6B39}",
        "irwin_IsFireCauseInvestigated": 1,
        "irwin_IsFireCodeRequested": 0,
        "irwin_IsFSAssisted": 1,
        "irwin_IsMultiJurisdictional": 0,
        "irwin_IsReimbursable": 0,
        "irwin_IsTrespass": 0,
        "irwin_IsUnifiedCommand": null,
        "irwin_LocalIncidentIdentifier": "000854",
        "irwin_PercentContained": null,
        "irwin_PercentPerToBeContained": null,
        "irwin_POOCity": null,
        "irwin_POOCounty": "Riverside",
        "irwin_POODispatchCenterID": "CASBCC",
        "irwin_POOFips": "06065",
        "irwin_POOJurisdictionalAgency": "BLM",
        "irwin_POOJurisdictionalUnit": "CACDD",
        "irwin_POOJurisdUnitParentUnit": null,
        "irwin_POOLandownerCategory": "BLM",
        "irwin_POOLandownerKind": "Federal",
        "irwin_POOLegalDescPrinMeridian": null,
        "irwin_POOLegalDescQtr": null,
        "irwin_POOLegalDescQtrQtr": null,
        "irwin_POOLegalDescRange": null,
        "irwin_POOLegalDescSection": null,
        "irwin_POOLegalDescTownship": null,
        "irwin_POOPredServiceAreaID": "SC12",
        "irwin_POOProtectingAgency": "BLM",
        "irwin_POOProtectingUnit": "CACDD",
        "irwin_POOState": "US-CA",
        "irwin_PredominantFuelGroup": "Grass",
        "irwin_PredominantFuelModel": "GR1",
        "irwin_PrimaryFuelModel": null,
        "irwin_SecondaryFuelModel": null,
        "irwin_TotalIncidentPersonnel": null,
        "irwin_UniqueFireIdentifier": "2022-CACDD-000854",
        "irwin_WFDSSDecisionStatus": "No Decision",
        "irwin_CreatedBySystem": "wildcad",
        "irwin_ModifiedBySystem": "wildcad",
        "irwin_IsDispatchComplete": 0,
        "irwin_OrganizationalAssessment": null,
        "irwin_StratDecisionPublishDate": null,
        "irwin_GlobalID": null,
        "irwin_Source": "IRWIN",
        "irwin_ArchivedOn": null,
        "irwin_ModifiedOnDateTime_dt": 1642358668137,
        "irwin_CreatedOnDateTime_dt": 1641956311070,
        "Shape__Area": 8.19909473648295e-10,
        "Shape__Length": 0.000108566439609677,
        "GlobalID": "1e23b4b3-e5f3-46f8-8579-b16598decd98",
        "irwin_IsCpxChild": 0,
        "irwin_CpxName": null,
        "irwin_CpxID": null
      }
    }
  ]
}
